{
    "id": 27345316,
    "title": "Boletín 4469-07",
    "url": "https://www.documentcloud.org/documents/27345316-boletin-4469-07/",
    "created_at": "2026-02-20 15:45:40.383407+00:00",
    "text": "Visita nuestro sitio web observatoriocongreso.cl\nMoción de los diputados señores Sepúlveda, don Roberto; Chahuán, Araya, Díaz del \nRío, Galilea, Kast, Martínez, Rojas y Sabag. \nModifica Código Penal con el fin de tipificar como delito de estafa, las conductas que \nmediante engaños e invocando la adhesión a determinadas creencias religiosas, persiguen la \ndisposición patrimonial en las formas que indica. (boletín N° 4469-071\n)\nFundamentos del proyecto.\nLa estafa se ha definido en general, como un delito mediante el cual el agente desarrolla una \nconducta revestida de engaño, para provocar en la víctima una disposición patrimonial en \nbeneficio del autor, que mediante este ardid se enriquece.\nNuestra legislación positiva, contiene en el párrafo 8, del Título VIII del Libro Segundo del \nCódigo Penal, la descripción de las figuras constitutivas de los delitos de estafas y otros \nengaños, asignándoseles las penas que para caso se contemplan.\nEl artículo 467 del referido texto legal sanciona la defraudación en la sustancia, cantidad o \ncalidad de las cosas, que se hayan entregado en virtud de un título obligatorio, imponiendo \ndiferentes penas, según sea el monto a que ascienda la respectiva defraudación.\nA su vez, el artículo 468 del mismo compendio normativo, establece que se aplican las penas \ndel citado artículo 467 a quien defraude usando nombre fingido, atribuyéndose poder, \ninfluencia o crédito supuestos, aparentando bienes, crédito, comisión, empresa o negociación \nimaginarios, o valiéndose de cualquier otro engaño semejante. \nNormalmente, en este tipo de conductas, el agente debe desplegar una acción bastante \nconvincente para lograr su objetivo, lo que en doctrina jurídica, se denomina “mise en scéne”, \nesto es, el montaje de un verdadero tinglado para crear el efecto propicio a la obtención del \npropósito que los anima.\nPor su parte, el artículo 469 de este código, contempla cinco conductas punibles constitutivas \nde estafas específicas, a las cuales se asigna las mismas penas señaladas en el artículo 467 \nantes mencionado.\nDel examen de las conductas descritas en dicho artículo 469, se puede concluir que todas \nellas dicen relación con defraudaciones en aspectos de carácter económico y mercantil. \nSin embargo, con el correr de los tiempos han surgido nuevas formas de estafa, que sin tener \nuna connotación económica propiamente tal, o ser de carácter comercial o mercantil, sus \nagentes ocupan otro tipo de engaños para lograr sus malévolos objetivos.\nPara dicho propósito, recurren a temas de gran sensibilidad para las personas, como lo es la \ngenuina búsqueda de una determinada fe o religión, y por consiguiente la creencia en \ndeterminados principios, como son la sanidad física, sicológica, emocional y espiritual, \ntratando de obtener la adhesión, observancia o práctica de las mismas.\n1 Cuenta del proyecto en la sesión Nº69 de la Cámara de Diputados (Legislatura Nº354) celebrada el día martes \n5 de septiembre de 2006. Paginas Nº87-88.\u0000\n\nVisita nuestro sitio web observatoriocongreso.cl\nPara este efecto, difunden mediante diversas formas, ya sea de propaganda publicitaria o \nvaliéndose de una supuesta condición de liderazgo espiritual, la oferta comercial de \nelementos que pregonan como representativos del mensaje y los efectos que suponen \ntransmitir, tales como imágenes, piedras, líquidos, cremas, supuestas reliquias de lugares \nsagrados, metales u otros similares, a los cuales les atribuyen poderes mágicos o de sanación \ndivina, similares a talismanes o amuletos, para persuadir acerca de la necesidad de su \ncompra, pero que a la postre, no son sino artefactos carentes de valor alguno, y que emplean \ncomo medio para lograr la disposición patrimonial que pretenden.\nTales conductas deleznables, que no constituyen sino una burda charlatanería, causan mayor \nimpacto en los sectores más desposeídos, que con la mejor disposición y fe, creen en la oferta \nque se les hace, ignorando que se está abusando de su adhesión o creencia a la religión a que \nse les pretende reclutar.\nConsideramos entonces, que estas acciones deben ser sancionadas en forma específica, para \ncuyo efecto, se hace necesario incorporar un artículo 468 bis al Código Penal, estableciendo \nsanciones para quienes, con dolo específico, esto es, con plena conciencia de la ilicitud con \nque actúan, cometan este tipo de delitos.\nEn virtud de las consideraciones antes expuestas, sometemos a la aprobación de la Cámara \nde Diputados, el siguiente\nPROYECTO DE LEY:\nArtículo único: Modifícase el Código Penal, mediante la incorporación del artículo 468 bis, \ndel siguiente tenor:\n“Artículo 468 bis: En iguales penas incurrirán los que, al hacer difusión de una determinada \ncreencia religiosa, efectuaren ventas de elementos representativos de la misma, a los que se \nles atribuyere poderes divinos o sobrenaturales, a sabiendas que no revisten las dotes o \nvirtudes que en la propaganda o publicidad de ellos se les otorga”.\u0000"
}