{
    "id": 27345449,
    "title": "Boletín 9056-11",
    "url": "https://www.documentcloud.org/documents/27345449-boletin-9056-11/",
    "created_at": "2026-02-20 16:12:20.352838+00:00",
    "text": "Visita nuestro sitio web observatoriocongreso.cl\nProyecto iniciado en moción de los señores diputados Morales, Barros, Kast, Melero, \nMoreira, Rosales, Salaberry, Van Rysselberghe, Ward y de la diputada señora \nHoffmann, doña María José.\nModifica el Código Sanitario, prohibiendo la venta de suplementos alimenticios a los \nmenores de edad. (boletín N°9056-111\n)\nLa salud de las personas desde siempre ha constituido un tema de suma importancia en las \npolíticas estatales, a partir de la necesidad de contar con una población sana desde todo punto \nde vista. A partir de su importancia nos encontramos ante un asunto que posee múltiples \nimplicaciones y matices que trascienden los márgenes puramente vinculados a las temáticas \ndel Ministerio de Salud.\nBajo esta perspectiva, nuestra sociedad cada vez más instruida en un marco de desarrollo \neconómico y social va experimentando cambios trascendentes que modifican las lógicas en \nsu actuar que las separan de lo que fue la sociedad chilena hace sólo 10 años. Tales desafíos \nnuevos y sumamente complejos demandan respuestas sensatas de la ciudadanía y de sus \ninstituciones para que en definitiva tales desafíos y metas no se conviertan en problemas \ninsalvables.\nAnte esto, el ejercicio del deporte o el desarrollo de una vida saludable, constituye un \nelemento de la máxima trascendencia para nuestra sociedad, felizmente nuestro país está \ntomando conciencia acera de la importancia que tiene para nuestra sociedad que los chilenos\ndestinen más horas de su vida a la práctica de algún deporte o actividad, hecha que imprime \na la sociedad chilena de múltiples efectos positivos alejándola de lacras tan deleznables como \nla droga, la delincuencia. Sin lugar a dudas programas como \"elige vivir sano\", o iniciativas \ntales como los denominados kioscos saludables en nuestros establecimientos educacionales, \nel aumento de horas de educación física, constituyen pasos importantes y sustentables en el \ntiempo contra estos males indicados.\nSin embargo también debemos reconocer que la práctica descontrolada de ejercicio físico, \nfundamentalmente en nuestros jóvenes, tampoco puede erigirse como una situación del todo \npositiva. En efecto fenómenos como la vigorexia constituyen nuevas patologías que afectan \nsilenciosamente a varios sectores de nuestra juventud, provocando trastornos en su cuerpo, \ngenerándose consecuencialmente graves anomalías en su fisiología física y también psíquica.\nVemos que menores de tan sólo 14 años consumen sustancias que por su naturaleza pueden \nocasionar severos trastornos desde el punto de vista cardíaco, cerebral o motor y frente a ello \nhay que tomar resguardos y prevenciones.\nEn la actualidad el excesivo consumo (y abuso) en consumir sustancias tales como \nsuplementos alimenticios para mejorar la figura y el rendimiento deportivo se ha extendido \nen función directa con la proliferación de una cultura de la competitividad y el excesivo \nexitismo y materialismo de nuestra sociedad, sin que se tenga en mente los efectos \nperjudiciales que tales costumbres pueden acarrear en el organismo.\n1 Cuenta del proyecto en la sesión Nº55 de la Cámara de Diputados (Legislatura Nº361) celebrada el día \nmiércoles 7 de agosto de 2013. Paginas Nº103-104.\u0000\n\nVisita nuestro sitio web observatoriocongreso.cl\nUno de ellos, sin lugar a dudas, lo constituyen los severos problemas hepáticos que causan \ntales sustancias, siendo los más propensos a su consumo desmedido y sin un mayor control \nmédico, los adolescentes.\nQue es así, como la presente moción parlamentaria tiene por objeto establecer ciertas \nrestricciones a la venta de tales sustancias alimenticias a los menores de edad, pretendiendo \npor lo mismo generar una alerta acerca de del daño que los suplementos alimenticios genera \nen el organismo de miles de adolescentes en nuestro país.\nEs así como la consagración de esta normativa que viene en regular la venta de estos \nsuplementos nos permitiría maximizar los efectos positivos que implica la práctica del \ndeporte en nuestro país, evitando con ello la proliferación de males vinculadas a la salud \nfísica y metal de nuestros niños a lo largo de todo el país.\nPROYECTO DE LEY\nARTÍCULO ÚNICO: Incorpórese un nuevo inciso final en el artículo 98 del Código \nsanitario, norma que se reproduce de la siguiente manera:\n\"Se prohíbe la venta de suplementos alimenticios destinados a acelerar el rendimiento físico \ny deportivo a menores de 18 años, sin receta médica'`\u0000"
}